pybmrb/ChemicalShift.py
pybmrb/ChemicalShiftStatistics.py
pybmrb/Histogram.py
pybmrb/Spectra.py
pybmrb/__init__.py
pybmrb-3.0.9.dist-info/LICENSE
pybmrb-3.0.9.dist-info/METADATA
pybmrb-3.0.9.dist-info/WHEEL
pybmrb-3.0.9.dist-info/top_level.txt
pybmrb-3.0.9.dist-info/RECORD
