Metadata-Version: 2.1
Name: pybmrb
Version: 3.0.9
Summary: PyBMRB provides tools for visualizing BMRB entries and  NMR-STAR files. Maintained by the BMRB.
Home-page: https://github.com/uwbmrb/PyBMRB
Author: Kumaran Baskaran
Author-email: baskaran@uchc.edu
License: MIT
Keywords: bmrb,nmr,nmrstar,biomagresbank,biological magnetic resonance bank,HSQC,TOCSY,Chemical shifts,Histogram
Classifier: Development Status :: 5 - Production/Stable
Classifier: Environment :: Console
Classifier: Programming Language :: Python :: 3 :: Only
Classifier: Programming Language :: Python :: 3.8
Classifier: Programming Language :: Python :: 3.9
Classifier: Programming Language :: Python :: 3.10
Classifier: Programming Language :: Python :: 3.11
Classifier: Programming Language :: Python :: 3.12
Classifier: Programming Language :: Python :: 3.13
Classifier: Intended Audience :: Education
Classifier: License :: OSI Approved :: MIT License
Classifier: Natural Language :: English
Classifier: Operating System :: MacOS
Classifier: Operating System :: POSIX :: Linux
Classifier: Operating System :: Microsoft :: Windows
Classifier: Topic :: Scientific/Engineering :: Bio-Informatics
Classifier: Topic :: Software Development :: Libraries
Classifier: Topic :: Software Development :: Libraries :: Python Modules
Requires-Python: >=3.7
License-File: LICENSE
Requires-Dist: pandas
Requires-Dist: requests (<=3,>=2.21.0)
Requires-Dist: plotly (>=4.1.0)
Requires-Dist: pynmrstar (>=3.0.4)
Requires-Dist: numpy (>1.15)
